graph_transformer_pytorch/__init__.py
graph_transformer_pytorch/graph_transformer_pytorch.py
graph_transformer_pytorch-0.1.1.dist-info/LICENSE
graph_transformer_pytorch-0.1.1.dist-info/METADATA
graph_transformer_pytorch-0.1.1.dist-info/WHEEL
graph_transformer_pytorch-0.1.1.dist-info/top_level.txt
graph_transformer_pytorch-0.1.1.dist-info/RECORD
