Metadata-Version: 2.1
Name: graph-transformer-pytorch
Version: 0.1.1
Summary: Graph Transformer - Pytorch
Home-page: https://github.com/lucidrains/graph-transformer-pytorch
Author: Phil Wang
Author-email: lucidrains@gmail.com
License: MIT
Keywords: artificial intelligence,deep learning,transformers,graphs
Classifier: Development Status :: 4 - Beta
Classifier: Intended Audience :: Developers
Classifier: Topic :: Scientific/Engineering :: Artificial Intelligence
Classifier: License :: OSI Approved :: MIT License
Classifier: Programming Language :: Python :: 3.6
License-File: LICENSE
Requires-Dist: einops (>=0.3)
Requires-Dist: rotary-embedding-torch
Requires-Dist: torch (>=1.6)
